smpai/__init__.py
smpai/fsm.py
smpai/builder/__init__.py
smpai/builder/builder.py
smpai/builder/parser.py
smpai/components/__init__.py
smpai/components/action.py
smpai/components/context.py
smpai/components/listener.py
smpai/components/state.py
smpai/components/transition.py
smpai-0.1.2a2.dist-info/LICENSE
smpai-0.1.2a2.dist-info/METADATA
smpai-0.1.2a2.dist-info/WHEEL
smpai-0.1.2a2.dist-info/top_level.txt
smpai-0.1.2a2.dist-info/RECORD
